whych/whych.py
whych/__main__.py
whych/__init__.py
whych-0.2.1.dist-info/METADATA
whych-0.2.1.dist-info/DESCRIPTION.rst
whych-0.2.1.dist-info/RECORD
whych-0.2.1.dist-info/metadata.json
whych-0.2.1.dist-info/WHEEL
whych-0.2.1.dist-info/top_level.txt
