Metadata-Version: 2.0
Name: whych
Version: 0.2.1
Summary: A module to find modules
Home-page: https://github.com/pdebuyl/whych
Author: Pierre de Buyl
Author-email: pdebuyl@pdebuyl.be
License: BSD
Platform: UNKNOWN
Classifier: License :: OSI Approved :: BSD License
Classifier: Programming Language :: Python :: 2.7
Classifier: Programming Language :: Python :: 3
Classifier: Topic :: Utilities
